



<odoo>
<data noupdate='1'>
    <!-- class PropertyType(models.Model):
    _name = "estate.property.type" -->
    <record id='property_type_house' model='estate.property.type'>
       <field name="name">House</field>
    </record>
    <record id='property_type_apartment' model='estate.property.type'>
       <field name="name">Apartment</field>
    </record>
    <record id='property_type_land' model='estate.property.type'>
       <field name="name">Land</field>
    </record>
<record id='property_type_villa' model='estate.property.type'>
    <field name="name">Villa</field>
</record>
<record id='property_type_condo' model='estate.property.type'>
    <field name="name">Condo</field>
</record>
<record id='property_type_townhouse' model='estate.property.type'>
    <field name="name">Townhouse</field>
</record>
<record id='property_type_cottage' model='estate.property.type'>
    <field name="name">Cottage</field>
</record>
<record id='property_type_farm' model='estate.property.type'>
    <field name="name">Farm</field>
</record>
<record id='property_type_mansion' model='estate.property.type'>
    <field name="name">Mansion</field>
</record>
<record id='property_type_bungalow' model='estate.property.type'>
    <field name="name">Bungalow</field>
</record>
<record id='property_type_penthouse' model='estate.property.type'>
    <field name="name">Penthouse</field>
</record>
<record id='property_type_castle' model='estate.property.type'>
    <field name="name">Castle</field>
</record>
<record id='property_type_ranch' model='estate.property.type'>
    <field name="name">Ranch</field>
</record>
<record id='property_type_chalet' model='estate.property.type'>
    <field name="name">Chalet</field>
</record>
<record id='property_type_duplex' model='estate.property.type'>
    <field name="name">Duplex</field>
</record>
<record id='property_type_studio' model='estate.property.type'>
    <field name="name">Studio</field>
</record>
<record id='property_type_loft' model='estate.property.type'>
    <field name="name">Loft</field>
</record>
<record id='property_type_mobile_home' model='estate.property.type'>
    <field name="name">Mobile Home</field>
</record>
<record id='property_type_warehouse' model='estate.property.type'>
    <field name="name">Warehouse</field>
</record>
<record id='property_type_office' model='estate.property.type'>
    <field name="name">Office</field>
</record>
<record id='property_type_retail' model='estate.property.type'>
    <field name="name">Retail</field>
</record>
<record id='property_type_industrial' model='estate.property.type'>
    <field name="name">Industrial</field>
</record>
<record id='property_type_hotel' model='estate.property.type'>
    <field name="name">Hotel</field>
</record>
  </data>
</odoo>